botintel/__init__.py
botintel/client.py
botintel/exceptions.py
botintel/image_client.py
botintel/models.py
botintel_sdk-0.0.4.dist-info/METADATA
botintel_sdk-0.0.4.dist-info/WHEEL
botintel_sdk-0.0.4.dist-info/top_level.txt
botintel_sdk-0.0.4.dist-info/RECORD
