Metadata-Version: 2.2
Name: botintel-sdk
Version: 0.0.4
Summary: Official Python SDK for BotIntel API
Home-page: https://github.com/DeveleplorAbdullahH/botintel
Author: Abdullah Huseynli
Author-email: botintelai1@gmail.com
Classifier: Programming Language :: Python :: 3
Classifier: License :: OSI Approved :: MIT License
Classifier: Operating System :: OS Independent
Requires-Python: >=3.6
Requires-Dist: requests<3.0.0,>=2.25.1
Dynamic: author
Dynamic: author-email
Dynamic: classifier
Dynamic: description
Dynamic: description-content-type
Dynamic: home-page
Dynamic: requires-dist
Dynamic: requires-python
Dynamic: summary
